{
  "operationConfig" : {
    "name" : "updatesportsnews4130",
    "type" : "MappedToBackend",
    "cachable" : false,
    "smsEnabled" : false,
    "security" : "public",
    "responseEncoding" : "UTF-8",
    "httpMethod" : "GET",
    "decodeResponseBody" : false,
    "referencingEndpoint" : "default",
    "inputs" : [ {
      "id" : "sportid",
      "scope" : "request",
      "dataType" : "number",
      "encode" : true,
      "passNull" : false
    }, {
      "id" : "stateId",
      "scope" : "request",
      "dataType" : "number",
      "encode" : true,
      "passNull" : false
    }, {
      "id" : "Date",
      "scope" : "request",
      "dataType" : "date",
      "encode" : true,
      "passNull" : false
    }, {
      "id" : "title",
      "scope" : "request",
      "dataType" : "string",
      "encode" : true,
      "passNull" : false
    }, {
      "id" : "description",
      "scope" : "request",
      "dataType" : "string",
      "encode" : true,
      "passNull" : false
    }, {
      "id" : "image1",
      "scope" : "request",
      "dataType" : "string",
      "encode" : true,
      "passNull" : false
    }, {
      "id" : "image2",
      "scope" : "request",
      "dataType" : "string",
      "encode" : true,
      "passNull" : false
    }, {
      "id" : "image3",
      "scope" : "request",
      "dataType" : "string",
      "encode" : true,
      "passNull" : false
    }, {
      "id" : "lastupdatetimestamp",
      "scope" : "request",
      "dataType" : "date",
      "encode" : true,
      "passNull" : false
    }, {
      "id" : "softdeleteflag",
      "scope" : "request",
      "dataType" : "number",
      "encode" : true,
      "passNull" : false
    }, {
      "id" : "state_newscol",
      "scope" : "request",
      "dataType" : "string",
      "encode" : true,
      "passNull" : false
    } ],
    "iMapping" : "<?xml version=\"1.0\" encoding=\"UTF-8\" standalone=\"yes\"?><mapper xmlns=\"http://www.kony.com/ns/mapper\"><map inputpath=\"request_in\" outputpath=\"request_out\"><exec-function name=\"kony.gen.obj.sports_news.toLOBFields\"/><exec-function name=\"kony.gen.obj.sports_news__metadata.toLOBFields\"/></map></mapper>",
    "oMapping" : "<?xml version=\"1.0\" encoding=\"UTF-8\" standalone=\"yes\"?><mapper xmlns=\"http://www.kony.com/ns/mapper\"><map inputpath=\"response_in\" outputpath=\"response_out\"><map inputpath=\"sports_news\" outputpath=\"sports_news\"><exec-function name=\"kony.gen.obj.sports_news.fromLOBFields\"/></map></map></mapper>",
    "applyCommonMapping" : true,
    "applyRequestCommonMapping" : true,
    "applyResponseCommonMapping" : true,
    "entityMetadata" : "{\"entityAttributeTypeList\":[{\"name\":\"sportid\",\"jdbcType\":4,\"columnTypeName\":\"INT\",\"columnDecimalDigits\":0,\"autoGenerated\":false,\"creatable\":true,\"updatable\":false,\"primary\":true,\"softDelete\":false,\"lastModified\":false},{\"name\":\"stateId\",\"jdbcType\":4,\"columnTypeName\":\"INT\",\"columnDecimalDigits\":0,\"autoGenerated\":false,\"creatable\":true,\"updatable\":false,\"primary\":true,\"softDelete\":false,\"lastModified\":false},{\"name\":\"Date\",\"jdbcType\":91,\"columnTypeName\":\"DATE\",\"columnDecimalDigits\":0,\"autoGenerated\":false,\"creatable\":true,\"updatable\":false,\"primary\":true,\"softDelete\":false,\"lastModified\":false},{\"name\":\"title\",\"jdbcType\":12,\"columnTypeName\":\"VARCHAR\",\"columnDecimalDigits\":0,\"autoGenerated\":false,\"creatable\":true,\"updatable\":true,\"primary\":false,\"softDelete\":false,\"lastModified\":false},{\"name\":\"description\",\"jdbcType\":12,\"columnTypeName\":\"VARCHAR\",\"columnDecimalDigits\":0,\"autoGenerated\":false,\"creatable\":true,\"updatable\":true,\"primary\":false,\"softDelete\":false,\"lastModified\":false},{\"name\":\"image1\",\"jdbcType\":-1,\"columnTypeName\":\"LONGTEXT\",\"columnDecimalDigits\":0,\"autoGenerated\":false,\"creatable\":true,\"updatable\":true,\"primary\":false,\"softDelete\":false,\"lastModified\":false},{\"name\":\"image2\",\"jdbcType\":-1,\"columnTypeName\":\"LONGTEXT\",\"columnDecimalDigits\":0,\"autoGenerated\":false,\"creatable\":true,\"updatable\":true,\"primary\":false,\"softDelete\":false,\"lastModified\":false},{\"name\":\"image3\",\"jdbcType\":-1,\"columnTypeName\":\"LONGTEXT\",\"columnDecimalDigits\":0,\"autoGenerated\":false,\"creatable\":true,\"updatable\":true,\"primary\":false,\"softDelete\":false,\"lastModified\":false},{\"name\":\"lastupdatetimestamp\",\"jdbcType\":93,\"columnTypeName\":\"TIMESTAMP\",\"columnDecimalDigits\":0,\"autoGenerated\":false,\"creatable\":true,\"updatable\":true,\"primary\":false,\"softDelete\":false,\"lastModified\":true},{\"name\":\"softdeleteflag\",\"jdbcType\":-6,\"columnTypeName\":\"TINYINT\",\"columnDecimalDigits\":0,\"autoGenerated\":false,\"creatable\":true,\"updatable\":true,\"primary\":false,\"softDelete\":true,\"lastModified\":false},{\"name\":\"state_newscol\",\"jdbcType\":12,\"columnTypeName\":\"VARCHAR\",\"columnDecimalDigits\":0,\"autoGenerated\":false,\"creatable\":true,\"updatable\":true,\"primary\":false,\"softDelete\":false,\"lastModified\":false}],\"relationshipTypeList\":[],\"name\":\"sports_news\",\"schemaName\":\"breakingnews\",\"entityType\":\"com.kony.rdbms.metadata.model.AnnotatedTable\"}",
    "opcode" : "update",
    "backendMeta" : {
      "qualifiedObjectName" : "breakingnews.sports_news",
      "backendObjectName" : "sports_news"
    },
    "relationshipHierarchyMapping" : {
      "children" : [ ],
      "name" : "sports_news",
      "actions" : {
        "create" : true,
        "update" : true,
        "delete" : true
      },
      "selected" : true
    },
    "requestXmlMappingOverride" : false,
    "responseXmlMappingOverride" : false
  }
}